tenacity/__init__.py
tenacity/_utils.py
tenacity/after.py
tenacity/before.py
tenacity/before_sleep.py
tenacity/nap.py
tenacity/py.typed
tenacity/retry.py
tenacity/stop.py
tenacity/tornadoweb.py
tenacity/wait.py
tenacity/asyncio/__init__.py
tenacity/asyncio/retry.py
tenacity-8.4.2.dist-info/LICENSE
tenacity-8.4.2.dist-info/METADATA
tenacity-8.4.2.dist-info/WHEEL
tenacity-8.4.2.dist-info/top_level.txt
tenacity-8.4.2.dist-info/RECORD
