Metadata-Version: 2.1
Name: tenacity
Version: 8.4.2
Summary: Retry code until it succeeds
Home-page: https://github.com/jd/tenacity
Author: Julien Danjou
Author-email: julien@danjou.info
License: Apache 2.0
Classifier: Intended Audience :: Developers
Classifier: License :: OSI Approved :: Apache Software License
Classifier: Programming Language :: Python
Classifier: Programming Language :: Python :: 3
Classifier: Programming Language :: Python :: 3 :: Only
Classifier: Programming Language :: Python :: 3.8
Classifier: Programming Language :: Python :: 3.9
Classifier: Programming Language :: Python :: 3.10
Classifier: Programming Language :: Python :: 3.11
Classifier: Programming Language :: Python :: 3.12
Classifier: Topic :: Utilities
Requires-Python: >=3.8
Provides-Extra: doc
Provides-Extra: test
License-File: LICENSE
